{
    "122.800": "UNICOM",
    "121.500": "GUARD",
    "123.000": "LOUNGE ROOM",
    "125.230": "LFLG_ATIS",
    "121.000": "LFLG_TWR-GND",
    "121.655": "LFLG_TWR-GND",
    "133.855": "LFLS_ATIS",
    "119.300": "LFLS_TWR-GND",
    "121.930": "LFLS_TWR-GND",
    "129.875": "LFBD_APP",
    "131.155": "LFBD_ATIS",
    "121.900": "LFBD_GND",
    "118.300": "LFBD_TWR",
    "121.155": "LFPG_APP",
    "128.230": "LFPG_ATIS",
    "121.610": "LFPG_GND",
    "119.250": "LFPG_TWR",
    "121.950": "LFPZ_GND",
    "118.000": "LFPZ_TWR",
    "121.900": "LFPX_GND",
    "129.525": "LFPX_TWR",
    "127.480": "LFPN_ATIS",
    "122.130": "LFPN_TWR-GND",
    "120.750": "LFPN_TWR-GND",
    "125.600": "LFBZ_APP",
    "128.230": "LFBZ_ATIS",
    "121.950": "LFBZ_GND",
    "118.700": "LFBZ_TWR",
    "123.065":"MONTAGNE"
}
